kalente/__init__.py
kalente/__main__.py
kalente/classes/__init__.py
kalente/classes/calendar.py
kalente/static/logo.png
kalente/templates/daily.html
kalente/templates/monthly.html
kalente/templates/weekly.html
kalente/templates/yearly.html
kalente-0.2.2.dist-info/METADATA
kalente-0.2.2.dist-info/WHEEL
kalente-0.2.2.dist-info/entry_points.txt
kalente-0.2.2.dist-info/licenses/LICENSE
kalente-0.2.2.dist-info/RECORD
