Metadata-Version: 2.4
Name: kalente
Version: 0.2.2
Summary: Simple Python script to generate a printable calendar
Project-URL: Homepage, https://kumig.it/kumitterer/kalente
Project-URL: Bug Tracker, https://kumig.it/kumitterer/kalente/issues
Author-email: Kumi Mitterer <kalente@kumi.email>
License: Copyright (c) 2023 Kumi Mitterer <kalente@kumi.email>
License-File: LICENSE
Classifier: License :: OSI Approved :: MIT License
Classifier: Operating System :: OS Independent
Classifier: Programming Language :: Python :: 3
Requires-Python: >=3.10
Requires-Dist: holidays
Requires-Dist: jinja2
Requires-Dist: pdfkit
Requires-Dist: python-dateutil
